{
  "switcher:open": [
    {
      "modifiers": [
        "Mod"
      ],
      "key": "O"
    },
    {
      "modifiers": [
        "Mod"
      ],
      "key": "E"
    }
  ],
  "markdown:toggle-preview": [],
  "command-palette:open": [
    {
      "modifiers": [
        "Mod",
        "Shift"
      ],
      "key": "P"
    }
  ],
  "workspace:split-vertical": [
    {
      "modifiers": [
        "Mod"
      ],
      "key": "P"
    }
  ],
  "app:toggle-left-sidebar": [
    {
      "modifiers": [
        "Alt"
      ],
      "key": "B"
    }
  ],
  "workspace:goto-tab-1": [],
  "workspace:goto-tab-2": [],
  "workspace:goto-tab-3": [],
  "workspace:goto-tab-4": [],
  "workspace:goto-tab-5": [],
  "workspace:goto-tab-7": [],
  "workspace:goto-tab-6": [],
  "workspace:goto-tab-8": [],
  "app:go-back": [
    {
      "modifiers": [
        "Mod"
      ],
      "key": "R"
    }
  ]
}